odoo/addons/project_task_stage_portal_user_visibility/README.rst
odoo/addons/project_task_stage_portal_user_visibility/__init__.py
odoo/addons/project_task_stage_portal_user_visibility/__manifest__.py
odoo/addons/project_task_stage_portal_user_visibility/hooks.py
odoo/addons/project_task_stage_portal_user_visibility/i18n/es.po
odoo/addons/project_task_stage_portal_user_visibility/models/__init__.py
odoo/addons/project_task_stage_portal_user_visibility/models/project_task_type.py
odoo/addons/project_task_stage_portal_user_visibility/security/ir_rule.xml
odoo/addons/project_task_stage_portal_user_visibility/static/description/icon.png
odoo/addons/project_task_stage_portal_user_visibility/views/project_views.xml
odoo_addon_project_task_stage_portal_user_visibility-16.0.1.0.0.2.dist-info/METADATA
odoo_addon_project_task_stage_portal_user_visibility-16.0.1.0.0.2.dist-info/WHEEL
odoo_addon_project_task_stage_portal_user_visibility-16.0.1.0.0.2.dist-info/top_level.txt
odoo_addon_project_task_stage_portal_user_visibility-16.0.1.0.0.2.dist-info/RECORD
